indexed_priority_queue/__init__.py
indexed_priority_queue/ipq.py
indexed_priority_queue-0.1.1.dist-info/LICENSE
indexed_priority_queue-0.1.1.dist-info/METADATA
indexed_priority_queue-0.1.1.dist-info/WHEEL
indexed_priority_queue-0.1.1.dist-info/top_level.txt
indexed_priority_queue-0.1.1.dist-info/RECORD
