Metadata-Version: 2.1
Name: indexed-priority-queue
Version: 0.1.1
Summary: A Python implementation of an Indexed Priority Queue (IPQ).
Home-page: https://github.com/gabrielbazan/indexed_priority_queue
Author: Gabriel Bazan
Author-email: gbazan@outlook.com
License: MIT
Classifier: Intended Audience :: Developers
Classifier: Programming Language :: Python
Classifier: Programming Language :: Python :: 3.6
Classifier: Programming Language :: Python :: 3.7
Classifier: Programming Language :: Python :: 3.8
Classifier: Programming Language :: Python :: 3.9
Classifier: Programming Language :: Python :: 3.10
Classifier: Programming Language :: Python :: 3 :: Only
Classifier: Operating System :: OS Independent
Requires-Python: >=3.6.2
License-File: LICENSE
